README.md
setup.cfg
setup.py
cipher/__init__.py
cipher/__main__.py
cipher/ui.py
cipher/utilities.py
cipher_symmetric.egg-info/PKG-INFO
cipher_symmetric.egg-info/SOURCES.txt
cipher_symmetric.egg-info/dependency_links.txt
cipher_symmetric.egg-info/entry_points.txt
cipher_symmetric.egg-info/top_level.txt