Metadata-Version: 2.1
Name: cipher-symmetric
Version: 1.0.1
Summary: UNKNOWN
Home-page: https://github.com/Programming-geek582/encipher
Author: PG
Author-email: htmlgeek752@gmail.com
License: UNKNOWN
Platform: UNKNOWN
Classifier: Programming Language :: Python :: 3
Classifier: License :: OSI Approved :: MIT License
Classifier: Operating System :: OS Independent
Classifier: Programming Language :: Python :: 3.8
Requires-Python: >=3.8
